MANIFEST.in
README.rst
setup.py
cish/__init__.py
cish/commands.py
cish/pyenv.py
cish/test_commands.py
cish/test_pyenv.py
cish.egg-info/PKG-INFO
cish.egg-info/SOURCES.txt
cish.egg-info/dependency_links.txt
cish.egg-info/top_level.txt