Metadata-Version: 1.0
Name: cish
Version: 0.2.1
Summary: Write shell-like python scripts to control continuous builds.
Home-page: https://github.com/smurn/cish
Author: Stefan C. Mueller
Author-email: scm@smurn.org
License: UNKNOWN
Platform: UNKNOWN
